otter_pensieve/__init__.py
otter_pensieve/answer_extraction.py
otter_pensieve/client.py
otter_pensieve/notebook_parsing.py
otter_pensieve/notebook_rendering.py
otter_pensieve/notebook_slicing.py
otter_pensieve/pdf_merging.py
otter_pensieve-1.6.0.dist-info/LICENSE
otter_pensieve-1.6.0.dist-info/METADATA
otter_pensieve-1.6.0.dist-info/WHEEL
otter_pensieve-1.6.0.dist-info/RECORD
