Metadata-Version: 2.3
Name: otter-pensieve
Version: 1.6.0
Summary: A plugin for `otter-grader` allowing the otter autograder to upload submission PDFs to Pensieve on students' behalfs.
License: MIT
Keywords: otter,pensieve
Author: Minjune Kim
Author-email: minjune@pensieve.co
Requires-Python: >=3.9,<4.0
Classifier: License :: OSI Approved :: MIT License
Classifier: Programming Language :: Python :: 3
Classifier: Programming Language :: Python :: 3.9
Classifier: Programming Language :: Python :: 3.10
Classifier: Programming Language :: Python :: 3.11
Classifier: Programming Language :: Python :: 3.12
Classifier: Programming Language :: Python :: 3.13
Requires-Dist: otter-grader (>=6.1.3)
Requires-Dist: pydantic (>=2.8.2,<3.0)
Requires-Dist: pypdf (>=5.6.0,<6.0.0)
Requires-Dist: requests (>=2.32.3,<3.0)
Requires-Dist: strip-ansi (==0.1.1)
